asyncsa/__init__.py
asyncsa/util.py
asyncsa/connection/__init__.py
asyncsa/connection/aio_mysql.py
asyncsa/connection/async_pg.py
asyncsa/connection/base.py
asyncsa/logger/__init__.py
asyncsa/logger/logger.py
asyncsa/manager/__init__.py
asyncsa/manager/aio_mysql.py
asyncsa/manager/async_pg.py
asyncsa/manager/base.py
asyncsa/model/__init__.py
asyncsa/model/mixin.py
asyncsa-2.0.2.dist-info/LICENSE
asyncsa-2.0.2.dist-info/METADATA
asyncsa-2.0.2.dist-info/WHEEL
asyncsa-2.0.2.dist-info/top_level.txt
asyncsa-2.0.2.dist-info/RECORD
