Metadata-Version: 2.1
Name: asyncsa
Version: 2.0.2
Summary: asyncio sqlalchemy support
Home-page: https://github.com/aohan237/asyncsa
Author: aohan237
Author-email: aohan237@gmail.com
License: MIT
Platform: POSIX
Classifier: License :: OSI Approved :: MIT License
Classifier: Development Status :: 4 - Beta
Classifier: Programming Language :: Python
Classifier: Programming Language :: Python :: 3
Classifier: Programming Language :: Python :: 3.6
Classifier: Operating System :: POSIX
Classifier: Environment :: Web Environment
Classifier: Intended Audience :: Developers
Classifier: Topic :: Software Development
Classifier: Topic :: Software Development :: Libraries
License-File: LICENSE
Requires-Dist: sqlalchemy
Requires-Dist: asyncpg
Requires-Dist: aiomysql
